qchem_inputgen/__init__.py
qchem_inputgen/__main__.py
qchem_inputgen/cli.py
qchem_inputgen/qchem.py
qchem_inputgen/xyz.py
qchem_inputgen-1.0.1.dist-info/licenses/LICENSE
qchem_inputgen-1.0.1.dist-info/METADATA
qchem_inputgen-1.0.1.dist-info/WHEEL
qchem_inputgen-1.0.1.dist-info/entry_points.txt
qchem_inputgen-1.0.1.dist-info/top_level.txt
qchem_inputgen-1.0.1.dist-info/RECORD
