Metadata-Version: 2.4
Name: qchem-inputgen
Version: 1.0.1
Summary: Generate Q-Chem input files from XYZ geometries (defaults geared toward MRSF).
Author-email: Arnab Chakraborty <arnabc20@usc.edu>
License: MIT
Project-URL: Homepage, https://github.com/achakra9/qchem_inputgen
Project-URL: Repository, https://github.com/achakra9/qchem_inputgen
Project-URL: Issues, https://github.com/achakra9/qchem_inputgen/issues
Keywords: quantum-chemistry,q-chem,chemistry,input-generator
Classifier: Programming Language :: Python :: 3
Classifier: License :: OSI Approved :: MIT License
Classifier: Operating System :: OS Independent
Requires-Python: >=3.10
License-File: LICENSE
Dynamic: license-file
